synapse_build/__init__.py
synapse_build/main.py
synapse_build-0.2.0.dist-info/LICENSE
synapse_build-0.2.0.dist-info/METADATA
synapse_build-0.2.0.dist-info/WHEEL
synapse_build-0.2.0.dist-info/top_level.txt
synapse_build-0.2.0.dist-info/RECORD
