Metadata-Version: 2.1
Name: synapse-build
Version: 0.2.0
Summary: Automated build for synapse workspace artifacts
Home-page: UNKNOWN
License: UNKNOWN
Platform: UNKNOWN
Requires-Dist: json
